{
  "opinions": [
    {
      "id": 1742896981123,
      "votes": 3,
      "userName": "adfsaga ",
      "title": "daf frgrgav ",
      "body": "E eef FSFGGG DAGFDH FGH R SGHS FHT SRH"
    },
    {
      "id": 1742896913281,
      "votes": 2,
      "userName": "adfsaga ",
      "title": "form acton s bs",
      "body": "forms action are now vailale in react 19"
    },
    {
      "id": 1742896335069,
      "votes": 2,
      "userName": "adfsaga ",
      "title": "aejfhehbb ",
      "body": "ejn jehuHU tnu3ihui*n H3FNJKN ; FKNJKN NN"
    },
    {
      "id": 1,
      "userName": "Max Scr",
      "title": "Do yourself a favor and learn React!",
      "body": "React is an amazing JavaScript library!\n\nDespite all it's shortcomings.",
      "votes": 1
    },
    {
      "id": 2,
      "userName": "Max Scr",
      "title": "React has more depth than you might first think!",
      "body": "React is a great library to learn, but it's not just about the basics. Dive deeper!\nFor example with this course!",
      "votes": 4
    }
  ]
}